schemagen/__init__.py
schemagen/__main__.py
schemagen/schemagen.py
schemagen/antlr/GraphQLLexer.py
schemagen/antlr/GraphQLListener.py
schemagen/antlr/GraphQLParser.py
schemagen/antlr/__init__.py
schemagen/codegen/__init__.py
schemagen/errors/__init__.py
schemagen/utils/__init__.py
schemagen-1.0.5.dist-info/LICENSE
schemagen-1.0.5.dist-info/METADATA
schemagen-1.0.5.dist-info/WHEEL
schemagen-1.0.5.dist-info/entry_points.txt
schemagen-1.0.5.dist-info/top_level.txt
schemagen-1.0.5.dist-info/RECORD
