Metadata-Version: 2.1
Name: schemagen
Version: 1.0.5
Summary: A Command line tool for generating Python GraphQL implementations(with Graphene) from GraphQL schema files
Home-page: https://github.com/GoZaddy/SchemaGen
Author: Faruq Yusuff
Author-email: faruqyusuff437@gmail.com
License: MIT
Keywords: graphql parser codegen
Platform: UNKNOWN
Classifier: Development Status :: 5 - Production/Stable
Classifier: License :: OSI Approved :: MIT License
Classifier: Intended Audience :: Developers
Requires-Python: >=3.6
Requires-Dist: antlr4-python3-runtime (==4.9.2)
Requires-Dist: autopep8 (==1.5.6)
